amazon_lex_helper/Disambiguation.py
amazon_lex_helper/IntentHandler.py
amazon_lex_helper/LexEvent.py
amazon_lex_helper/LexEventDispatcher.py
amazon_lex_helper/LexResponse.py
amazon_lex_helper/__init__.py
amazon_lex_helper-1.1.dist-info/LICENSE
amazon_lex_helper-1.1.dist-info/METADATA
amazon_lex_helper-1.1.dist-info/WHEEL
amazon_lex_helper-1.1.dist-info/top_level.txt
amazon_lex_helper-1.1.dist-info/RECORD
